huntertray/__init__.py
huntertray/appindicator_replacement.py
huntertray/chrome.py
huntertray/firefox.py
huntertray/producthunt.py
huntertray/version.py
huntertray/data/__init__.py
huntertray/data/hunter-tray.png
huntertray-0.0.3.dist-info/METADATA
huntertray-0.0.3.dist-info/WHEEL
huntertray-0.0.3.dist-info/entry_points.txt
huntertray-0.0.3.dist-info/top_level.txt
huntertray-0.0.3.dist-info/RECORD
