Metadata-Version: 2.1
Name: huntertray
Version: 0.0.3
Summary: ProductHunt in your System Tray
Home-page: https://github.com/artiya4u/huntertray
Author: Artiya Thinkumpang
Author-email: artiya4u@gmail.com
License: MIT
Keywords: ProductHunt PH tray system tray icon huntertray
Platform: UNKNOWN
Requires-Dist: requests (>=2.2.1)
